github_repo_seo_optimizer-0.1.0.dist-info/licenses/LICENSE
repo_seo/__init__.py
repo_seo/ai_client.py
repo_seo/analyzer.py
repo_seo/batch.py
repo_seo/cli.py
repo_seo/file_generators.py
repo_seo/main.py
repo_seo/sync.py
github_repo_seo_optimizer-0.1.0.dist-info/METADATA
github_repo_seo_optimizer-0.1.0.dist-info/WHEEL
github_repo_seo_optimizer-0.1.0.dist-info/entry_points.txt
github_repo_seo_optimizer-0.1.0.dist-info/top_level.txt
github_repo_seo_optimizer-0.1.0.dist-info/RECORD
