Metadata-Version: 2.4
Name: github-repo-seo-optimizer
Version: 0.1.0
Summary: A tool to optimize GitHub repositories for better discoverability through improved descriptions, topics, and documentation
Home-page: https://github.com/chenxingqiang/repo-seo
Author: Chen Xingqiang
Author-email: Chen Xingqiang <chenxingqiang@gmail.com>
Maintainer-email: Chen Xingqiang <chenxingqiang@gmail.com>
License: MIT License
Project-URL: Homepage, https://github.com/chenxingqiang/repo-seo
Project-URL: Documentation, https://github.com/chenxingqiang/repo-seo#readme
Project-URL: Repository, https://github.com/chenxingqiang/repo-seo
Project-URL: Issues, https://github.com/chenxingqiang/repo-seo/issues
Keywords: github,seo,repository,optimization,llm,ai,automation,git,documentation
Classifier: Development Status :: 4 - Beta
Classifier: Intended Audience :: Developers
Classifier: License :: OSI Approved :: MIT License
Classifier: Operating System :: OS Independent
Classifier: Programming Language :: Python :: 3
Classifier: Programming Language :: Python :: 3.8
Classifier: Programming Language :: Python :: 3.9
Classifier: Programming Language :: Python :: 3.10
Classifier: Programming Language :: Python :: 3.11
Classifier: Programming Language :: Python :: 3.12
Classifier: Topic :: Software Development :: Version Control :: Git
Requires-Python: >=3.8
License-File: LICENSE
Requires-Dist: click>=8.0.0
Requires-Dist: requests>=2.25.0
Requires-Dist: pyyaml>=5.4.0
Requires-Dist: rich>=10.0.0
Requires-Dist: python-dotenv>=0.19.0
Provides-Extra: dev
Requires-Dist: pytest>=7.0.0; extra == "dev"
Requires-Dist: pytest-cov>=3.0.0; extra == "dev"
Requires-Dist: pytest-asyncio>=0.18.0; extra == "dev"
Requires-Dist: black>=22.0.0; extra == "dev"
Requires-Dist: isort>=5.10.0; extra == "dev"
Requires-Dist: flake8>=4.0.0; extra == "dev"
Requires-Dist: mypy>=0.950; extra == "dev"
Requires-Dist: pre-commit>=2.17.0; extra == "dev"
Provides-Extra: openai
Requires-Dist: openai>=1.0.0; extra == "openai"
Provides-Extra: anthropic
Requires-Dist: anthropic>=0.3.0; extra == "anthropic"
Provides-Extra: gemini
Requires-Dist: google-generativeai>=0.3.0; extra == "gemini"
Provides-Extra: all
Requires-Dist: openai>=1.0.0; extra == "all"
Requires-Dist: anthropic>=0.3.0; extra == "all"
Requires-Dist: google-generativeai>=0.3.0; extra == "all"
Dynamic: author
Dynamic: home-page
Dynamic: license-file
Dynamic: requires-python
